slack_pybot/__init__.py
slack_pybot/bot.py
slack_pybot/data.py
slack_pybot-0.0.3.dist-info/METADATA
slack_pybot-0.0.3.dist-info/RECORD
slack_pybot-0.0.3.dist-info/WHEEL
slack_pybot-0.0.3.dist-info/top_level.txt
