Metadata-Version: 2.1
Name: slack-pybot
Version: 0.0.3
Summary: slackbot written in python 3.7
Home-page: https://github.com/albertywu/pybot
Author: Albert Wu
Author-email: albertywu@gmail.com
License: UNKNOWN
Platform: UNKNOWN
Classifier: Programming Language :: Python :: 3.7
Classifier: License :: OSI Approved :: MIT License
Classifier: Operating System :: OS Independent
